AUTHORS
ChangeLog
LICENSE
MANIFEST.in
README.md
requirements.txt
setup.py
bingo_tweets/__init__.py
bingo_tweets/admin.py
bingo_tweets/models.py
bingo_tweets/locale/de/LC_MESSAGES/django.po
django_bingo_tweets.egg-info/PKG-INFO
django_bingo_tweets.egg-info/SOURCES.txt
django_bingo_tweets.egg-info/dependency_links.txt
django_bingo_tweets.egg-info/requires.txt
django_bingo_tweets.egg-info/top_level.txt